quart/__init__.py
quart/__main__.py
quart/app.py
quart/asgi.py
quart/blueprints.py
quart/cli.py
quart/config.py
quart/ctx.py
quart/datastructures.py
quart/debug.py
quart/formparser.py
quart/globals.py
quart/helpers.py
quart/json/__init__.py
quart/json/provider.py
quart/json/tag.py
quart/logging.py
quart/py.typed
quart/routing.py
quart/sessions.py
quart/signals.py
quart/templating.py
quart/testing/__init__.py
quart/testing/app.py
quart/testing/client.py
quart/testing/connections.py
quart/testing/utils.py
quart/typing.py
quart/utils.py
quart/views.py
quart/wrappers/__init__.py
quart/wrappers/base.py
quart/wrappers/request.py
quart/wrappers/response.py
quart/wrappers/websocket.py
quart-0.19.7.dist-info/LICENSE
quart-0.19.7.dist-info/METADATA
quart-0.19.7.dist-info/WHEEL
quart-0.19.7.dist-info/entry_points.txt
quart-0.19.7.dist-info/RECORD
