Metadata-Version: 2.1
Name: Quart
Version: 0.19.7
Summary: A Python ASGI web microframework with the same API as Flask
Home-page: https://github.com/pallets/quart/
License: MIT
Author: pgjones
Author-email: philip.graham.jones@googlemail.com
Requires-Python: >=3.8
Classifier: Development Status :: 4 - Beta
Classifier: Environment :: Web Environment
Classifier: Intended Audience :: Developers
Classifier: License :: OSI Approved :: MIT License
Classifier: Operating System :: OS Independent
Classifier: Programming Language :: Python
Classifier: Programming Language :: Python :: 3
Classifier: Programming Language :: Python :: 3.8
Classifier: Programming Language :: Python :: 3.9
Classifier: Programming Language :: Python :: 3.10
Classifier: Programming Language :: Python :: 3.11
Classifier: Programming Language :: Python :: 3.12
Classifier: Programming Language :: Python :: 3.13
Classifier: Topic :: Internet :: WWW/HTTP :: Dynamic Content
Classifier: Topic :: Software Development :: Libraries :: Python Modules
Provides-Extra: docs
Provides-Extra: dotenv
Requires-Dist: aiofiles
Requires-Dist: blinker (>=1.6)
Requires-Dist: click (>=8.0.0)
Requires-Dist: flask (>=3.0.0)
Requires-Dist: hypercorn (>=0.11.2)
Requires-Dist: importlib_metadata ; python_version < "3.10"
Requires-Dist: itsdangerous
Requires-Dist: jinja2
Requires-Dist: markupsafe
Requires-Dist: pydata_sphinx_theme ; extra == "docs"
Requires-Dist: python-dotenv ; extra == "dotenv"
Requires-Dist: typing_extensions ; python_version < "3.10"
Requires-Dist: werkzeug (>=3.0.0)
Project-URL: Documentation, https://quart.palletsprojects.com
Project-URL: Repository, https://github.com/pallets/quart/
